RAMP/__init__.py
RAMP/commands_discovery.py
RAMP/common.py
RAMP/config.py
RAMP/disposableredis/__init__.py
RAMP/module_metadata.py
RAMP/packer.py
RAMP/ramp.py
RAMP/unpacker.py
RAMP/version.py
ramp_packer-2.5.16.dist-info/METADATA
ramp_packer-2.5.16.dist-info/WHEEL
ramp_packer-2.5.16.dist-info/entry_points.txt
ramp_packer-2.5.16.dist-info/licenses/LICENSE
ramp_packer-2.5.16.dist-info/RECORD
