Metadata-Version: 2.4
Name: ramp-packer
Version: 2.5.16
Summary: Packs for Redis modules into a distributable format
License: BSD-2-Clause
License-File: LICENSE
Author: Redis OSS
Author-email: oss@redis.com
Requires-Python: >=3.7,<4
Classifier: Development Status :: 4 - Beta
Classifier: Intended Audience :: Developers
Classifier: License :: OSI Approved :: BSD License
Classifier: Programming Language :: Python
Classifier: Programming Language :: Python :: 3
Classifier: Programming Language :: Python :: 3.7
Classifier: Programming Language :: Python :: 3.8
Classifier: Programming Language :: Python :: 3.9
Classifier: Programming Language :: Python :: 3.10
Classifier: Programming Language :: Python :: 3.11
Classifier: Programming Language :: Python :: 3.12
Classifier: Programming Language :: Python :: 3.13
Classifier: Programming Language :: Python :: 3.14
Classifier: Topic :: Database
Requires-Dist: PyYAML (>=6.0,<7.0)
Requires-Dist: click (>=8,<9)
Requires-Dist: distro (>=1.8,<2.0)
Requires-Dist: redis (>=4.1.0)
Requires-Dist: semantic-version (>=2.8.5,<3.0.0)
